number2text/number2text.py
number2text/lang/af.py
number2text/lang/am.py
number2text/lang/ar.py
number2text/lang/az.py
number2text/lang/be.py
number2text/lang/bn.py
number2text/lang/bs.py
number2text/lang/ca.py
number2text/lang/ceb.py
number2text/lang/ckb.py
number2text/lang/co.py
number2text/lang/cs.py
number2text/lang/cy.py
number2text/lang/da.py
number2text/lang/de.py
number2text/lang/el.py
number2text/lang/en.py
number2text/lang/eo.py
number2text/lang/es.py
number2text/lang/et.py
number2text/lang/eu.py
number2text/lang/fa.py
number2text/lang/fi.py
number2text/lang/fil.py
number2text/lang/fr.py
number2text/lang/fy.py
number2text/lang/ga.py
number2text/lang/gl.py
number2text/lang/gu.py
number2text/lang/ha.py
number2text/lang/he.py
number2text/lang/hr.py
number2text/lang/hu.py
number2text/lang/hy.py
number2text/lang/id.py
number2text/lang/ig.py
number2text/lang/is.py
number2text/lang/it.py
number2text/lang/ja.py
number2text/lang/jv.py
number2text/lang/ka.py
number2text/lang/kk.py
number2text/lang/km.py
number2text/lang/kn.py
number2text/lang/ko.py
number2text/lang/ku.py
number2text/lang/ky.py
number2text/lang/lo.py
number2text/lang/lt.py
number2text/lang/lv.py
number2text/lang/mg.py
number2text/lang/mk.py
number2text/lang/ml.py
number2text/lang/mn.py
number2text/lang/mr.py
number2text/lang/ms.py
number2text/lang/mt.py
number2text/lang/my.py
number2text/lang/nb.py
number2text/lang/ne.py
number2text/lang/nl.py
number2text/lang/nn.py
number2text/lang/ny.py
number2text/lang/or.py
number2text/lang/pa.py
number2text/lang/pl.py
number2text/lang/ps.py
number2text/lang/pt.py
number2text/lang/ro.py
number2text/lang/ru.py
number2text/lang/sd.py
number2text/lang/si.py
number2text/lang/sk.py
number2text/lang/sl.py
number2text/lang/so.py
number2text/lang/sq.py
number2text/lang/sr.py
number2text/lang/su.py
number2text/lang/sv.py
number2text/lang/sw.py
number2text/lang/ta.py
number2text/lang/te.py
number2text/lang/tg.py
number2text/lang/th.py
number2text/lang/tk.py
number2text-0.0.1.dist-info/METADATA
number2text-0.0.1.dist-info/WHEEL
number2text-0.0.1.dist-info/licenses/LICENSE
number2text-0.0.1.dist-info/RECORD
