Metadata-Version: 2.3
Name: number2text
Version: 0.0.1
Summary: Convert any number to string. Support ~100 langs
Project-URL: Homepage, https://github.com/daswer123/number2text
Project-URL: Bug Tracker, https://github.com/daswer123/number2text/issues
Author-email: daswer123 <daswerq123@gmail.com>
License-File: LICENSE
Classifier: License :: OSI Approved :: MIT License
Classifier: Operating System :: OS Independent
Classifier: Programming Language :: Python :: 3
Requires-Python: >=3.9
